supervised_FCN/__init__.py
supervised_FCN/example_compute_FID.py
supervised_FCN/example_compute_IS.py
supervised_FCN/example_data_loading.py
supervised_FCN/example_pretrained_model_loading.py
supervised_FCN/train_fcn.py
supervised_FCN/train_fcn_all_datasets.py
supervised_FCN/datasets/DataSummary_UCR.csv
supervised_FCN/datasets/__init__.py
supervised_FCN/experiments/__init__.py
supervised_FCN/experiments/exp_base.py
supervised_FCN/experiments/exp_train.py
supervised_FCN/models/__init__.py
supervised_FCN/models/fcn.py
supervised_FCN/preprocessing/__init__.py
supervised_FCN/preprocessing/augmentations.py
supervised_FCN/preprocessing/data_pipeline.py
supervised_FCN/preprocessing/preprocess_ucr.py
supervised_FCN/preprocessing/preprocess_uea.py
supervised_FCN/saved_models/__init__.py
supervised_FCN/utils/__init__.py
supervised_fcn-1.7.9.dist-info/LICENSE
supervised_fcn-1.7.9.dist-info/METADATA
supervised_fcn-1.7.9.dist-info/WHEEL
supervised_fcn-1.7.9.dist-info/top_level.txt
supervised_fcn-1.7.9.dist-info/RECORD
